README.md
setup.py
monero/__init__.py
monero_python.egg-info/PKG-INFO
monero_python.egg-info/SOURCES.txt
monero_python.egg-info/dependency_links.txt
monero_python.egg-info/top_level.txt